cvrp/__init__.py
cvrp/cli.py
cvrp/cvrp.py
cvrp-0.1.0.dist-info/METADATA
cvrp-0.1.0.dist-info/WHEEL
cvrp-0.1.0.dist-info/top_level.txt
cvrp-0.1.0.dist-info/RECORD
