Metadata-Version: 2.1
Name: cvrp
Version: 0.1.0
Summary: A Python implementation for solving the Capacitated Vehicle Routing Problem (CVRP) using heuristic and metaheuristic algorithms
Author: Alikacem Faycal
Author-email: faycal213.dz@gmail.com
License: The unlicense
Project-URL: Source, https://github.com/Faycal214/Vehicle-Routing-Problem
Classifier: Development Status :: 3 - Alpha
Classifier: Intended Audience :: Science/Research
Classifier: Intended Audience :: Developers
Classifier: Programming Language :: Python :: 3.11
Classifier: Programming Language :: Python :: 3.12
Classifier: Topic :: Utilities
Requires-Python: >= 3.10, <3.13
Requires-Dist: numpy
Requires-Dist: random
Requires-Dist: matplotlib
Requires-Dist: networkx
